{
    "prefix": "вд ",
    "farm": {
        "on": true,
        "soft": false,
        "last_time": 1646576440.4963863
    },
    "catcher": 2,
    "friends_add": true,
    "dogs_del": false,
    "ignore_list": [],
    "del_requests": false,
    "online": false,
    "offline": false,
    "templates_bind": 0,
    "trusted_users": [],
    "delete": {
        "deleter": "дд",
        "editor": "&#8300;",
        "editcmd": true,
        "old_type": true
    },
    "mentions": {
        "all": false,
        "mine": false
    },
    "leave_chats": false,
    "autostatus_on": false,
    "autostatus_format": "",
    "repeater": {
        "on": true,
        "prefix": "вд"
    },
    "added_by": 83759702,
    "user_id": 156680078,
    "vk_longpoll": true
}